wayparam/__init__.py
wayparam/__main__.py
wayparam/cli.py
wayparam/filters.py
wayparam/http.py
wayparam/io.py
wayparam/normalize.py
wayparam/output.py
wayparam/ratelimit.py
wayparam/wayback.py
wayparam-0.3.0.dist-info/licenses/LICENSE
wayparam-0.3.0.dist-info/METADATA
wayparam-0.3.0.dist-info/WHEEL
wayparam-0.3.0.dist-info/entry_points.txt
wayparam-0.3.0.dist-info/top_level.txt
wayparam-0.3.0.dist-info/RECORD
