Metadata-Version: 2.4
Name: wayparam
Version: 0.3.0
Summary: Fetch and normalize parameterized URLs from the Internet Archive Wayback CDX API (OSINT-friendly).
Author: Alessandro Greco
License: GPL-3.0
Project-URL: Homepage, https://aleff-github.github.io/wayparam/
Project-URL: Repository, https://github.com/aleff-github/wayparam
Project-URL: Issues, https://github.com/aleff-github/wayparam/issues
Keywords: osint,wayback,url,parameters,security
Classifier: Programming Language :: Python :: 3
Classifier: Programming Language :: Python :: 3 :: Only
Classifier: License :: OSI Approved :: GNU General Public License v3 (GPLv3)
Classifier: Operating System :: OS Independent
Classifier: Environment :: Console
Classifier: Topic :: Security
Classifier: Topic :: Internet :: WWW/HTTP
Requires-Python: >=3.9
License-File: LICENSE
Requires-Dist: httpx>=0.26.0
Provides-Extra: dev
Requires-Dist: pytest>=8.0.0; extra == "dev"
Requires-Dist: ruff>=0.6.0; extra == "dev"
Dynamic: license-file
